{
  "id": "content-author-split-01",
  "name": "Author Split",
  "category": "layouts",
  "style": ["editorial", "classic", "minimal"],
  "mood": ["professional", "trustworthy", "calm"],
  "layout": "split",
  "density": "low",
  "slots": [
    { "name": "bannerImage", "type": "image", "aspectRatio": "2:1" },
    { "name": "bannerImageAlt", "type": "text", "maxLength": 120 },
    { "name": "authorImage", "type": "image", "aspectRatio": "1:1" },
    { "name": "authorImageAlt", "type": "text", "maxLength": 120 },
    { "name": "authorName", "type": "text", "maxLength": 60 },
    { "name": "authorTagline", "type": "text", "maxLength": 200 },
    { "name": "description", "type": "text", "maxLength": 600 },
    { "name": "ctaText", "type": "text", "optional": true, "maxLength": 30 },
    { "name": "ctaUrl", "type": "url", "optional": true }
  ],
  "mobileBehavior": "stack",
  "pairsWell": [
    "hero-geometric-01",
    "testimonials-scrolling-01",
    "content-features-list-01",
    "stats-count-up-01"
  ],
  "pairsPoorly": ["content-statement-split-01"]
}
